antenny_cdk/__init__.py
antenny_cdk/py.typed
antenny_cdk/_jsii/__init__.py
antenny_cdk/_jsii/antenny-cdk@2.1.0.jsii.tgz
antenny_cdk-2.1.0.dist-info/METADATA
antenny_cdk-2.1.0.dist-info/WHEEL
antenny_cdk-2.1.0.dist-info/top_level.txt
antenny_cdk-2.1.0.dist-info/RECORD
