Metadata-Version: 2.1
Name: antenny-cdk
Version: 2.1.0
Summary: cdk constructs for antenny
Home-page: https://github.com/antenny/antenny-cdk.git
Author: Jacob Breindel
License: MIT
Project-URL: Source, https://github.com/antenny/antenny-cdk.git
Platform: UNKNOWN
Classifier: Intended Audience :: Developers
Classifier: Operating System :: OS Independent
Classifier: Programming Language :: JavaScript
Classifier: Programming Language :: Python :: 3 :: Only
Classifier: Programming Language :: Python :: 3.6
Classifier: Programming Language :: Python :: 3.7
Classifier: Programming Language :: Python :: 3.8
Classifier: Programming Language :: Python :: 3.9
Classifier: Typing :: Typed
Classifier: License :: OSI Approved
Requires-Python: >=3.6
Requires-Dist: aws-cdk.aws-iam (<2.0.0,>=1.82.0)
Requires-Dist: aws-cdk.aws-lambda (<2.0.0,>=1.82.0)
Requires-Dist: aws-cdk.aws-logs (<2.0.0,>=1.82.0)
Requires-Dist: aws-cdk.core (<2.0.0,>=1.82.0)
Requires-Dist: aws-cdk.custom-resources (<2.0.0,>=1.82.0)
Requires-Dist: jsii (<2.0.0,>=1.16.0)
Requires-Dist: publication (>=0.0.3)
